HISTORY.rst
LICENSE
MANIFEST.in
README.md
setup.py
singleurlcrud/__init__.py
singleurlcrud/tests.py
singleurlcrud/views.py
singleurlcrud/widgets.py
singleurlcrud.egg-info/PKG-INFO
singleurlcrud.egg-info/SOURCES.txt
singleurlcrud.egg-info/dependency_links.txt
singleurlcrud.egg-info/requires.txt
singleurlcrud.egg-info/top_level.txt
singleurlcrud/static/singleurlcrud/css/crud.css
singleurlcrud/static/singleurlcrud/js/crud-controller.js
singleurlcrud/static/singleurlcrud/js/jquery.formset.js
singleurlcrud/templates/singleurlcrud/delete.html
singleurlcrud/templates/singleurlcrud/dummy_extends_template.html
singleurlcrud/templates/singleurlcrud/edit.html
singleurlcrud/templates/singleurlcrud/list.html
singleurlcrud/templates/singleurlcrud/render_item.html
singleurlcrud/templatetags/__init__.py
singleurlcrud/templatetags/__init__.pyc
singleurlcrud/templatetags/crud_tags.py
singleurlcrud/templatetags/crud_tags.pyc