Metadata-Version: 1.1
Name: singleurlcrud
Version: 0.21
Summary: Django CRUD using a single view and hence a single URL.
Home-page: https://www.github.com/harikvpy/crud/
Author: Hari Mahadevan
Author-email: hari@hari.xyz
License: BSD-3
Keywords: django,crud,singleurlcrud
Platform: UNKNOWN
Classifier: Development Status :: 4 - Beta
Classifier: Environment :: Web Environment
Classifier: Framework :: Django
Classifier: Intended Audience :: Developers
Classifier: License :: OSI Approved :: BSD License
Classifier: Operating System :: OS Independent
Classifier: Programming Language :: Python :: 2.7
